pyfitnesspal/__init__.py
pyfitnesspal-0.1.0.dist-info/LICENSE
pyfitnesspal-0.1.0.dist-info/METADATA
pyfitnesspal-0.1.0.dist-info/WHEEL
pyfitnesspal-0.1.0.dist-info/RECORD
