Metadata-Version: 2.1
Name: pyfitnesspal
Version: 0.1.0
Summary: Unofficial Python client for MyFitnessPal API
License: MIT
Author: hexponent
Author-email: hexponent@proton.me
Requires-Python: >=3.9,<4.0
Classifier: License :: OSI Approved :: MIT License
Classifier: Programming Language :: Python :: 3
Classifier: Programming Language :: Python :: 3.9
Classifier: Programming Language :: Python :: 3.10
Classifier: Programming Language :: Python :: 3.11
Classifier: Programming Language :: Python :: 3.12
Requires-Dist: requests-oauthlib (>=2.0.0,<3.0.0)
